napari_tracing/__init__.py
napari_tracing/_combobox.py
napari_tracing/_dialog_widget.py
napari_tracing/_layer_model.py
napari_tracing/_logger.py
napari_tracing/_segment_model.py
napari_tracing/_trace_loader.py
napari_tracing/_trace_saver.py
napari_tracing/_widget.py
napari_tracing/napari.yaml
napari_tracing/point.py
napari_tracing/utils.py
napari_tracing/_tests/__init__.py
napari_tracing/_tests/test_widget.py
napari_tracing-1.0.2.dist-info/LICENSE
napari_tracing-1.0.2.dist-info/METADATA
napari_tracing-1.0.2.dist-info/WHEEL
napari_tracing-1.0.2.dist-info/entry_points.txt
napari_tracing-1.0.2.dist-info/top_level.txt
napari_tracing-1.0.2.dist-info/RECORD
