Metadata-Version: 2.1
Name: napari-tracing
Version: 1.0.2
Summary: A plugin to trace the brightest path between two points in an image
Home-page: https://github.com/mapmanager/napari-tracing
Author: Vasudha Jha
Author-email: reachvasudha27@gmail.com
License: GPL-3.0-only
Project-URL: Bug Tracker, https://github.com/mapmanager/napari-tracing/issues
Project-URL: Documentation, https://github.com/mapmanager/napari-tracing#README.md
Project-URL: Source Code, https://github.com/mapmanager/napari-tracing
Project-URL: User Support, https://github.com/mapmanager/napari-tracing/issues
Classifier: Development Status :: 2 - Pre-Alpha
Classifier: Framework :: napari
Classifier: Intended Audience :: Developers
Classifier: License :: OSI Approved :: GNU General Public License v3 (GPLv3)
Classifier: Operating System :: OS Independent
Classifier: Programming Language :: Python
Classifier: Programming Language :: Python :: 3
Classifier: Programming Language :: Python :: 3 :: Only
Classifier: Programming Language :: Python :: 3.8
Classifier: Programming Language :: Python :: 3.9
Classifier: Programming Language :: Python :: 3.10
Classifier: Topic :: Scientific/Engineering :: Image Processing
Requires-Python: >=3.8
License-File: LICENSE
Requires-Dist: numpy
Requires-Dist: qtpy
Requires-Dist: brightest-path-lib
Provides-Extra: testing
Requires-Dist: tox ; extra == 'testing'
Requires-Dist: pytest ; extra == 'testing'
Requires-Dist: pytest-cov ; extra == 'testing'
Requires-Dist: pytest-qt ; extra == 'testing'
Requires-Dist: napari ; extra == 'testing'
Requires-Dist: pyqt5 ; extra == 'testing'
